contact_phones_local/__init__.py
contact_phones_local/contact_phones_local.py
contact_phones_local/contact_phones_local_constants.py
contact_phones_local-0.0.8.dist-info/METADATA
contact_phones_local-0.0.8.dist-info/WHEEL
contact_phones_local-0.0.8.dist-info/top_level.txt
contact_phones_local-0.0.8.dist-info/RECORD
